odoo/addons/invader_payment_adyen_klarna_capture_delivery/README.rst
odoo/addons/invader_payment_adyen_klarna_capture_delivery/__init__.py
odoo/addons/invader_payment_adyen_klarna_capture_delivery/__manifest__.py
odoo/addons/invader_payment_adyen_klarna_capture_delivery/i18n/invader_payment_adyen_klarna_capture_delivery.pot
odoo/addons/invader_payment_adyen_klarna_capture_delivery/models/__init__.py
odoo/addons/invader_payment_adyen_klarna_capture_delivery/models/stock_picking.py
odoo/addons/invader_payment_adyen_klarna_capture_delivery/readme/CONTRIBUTORS.rst
odoo/addons/invader_payment_adyen_klarna_capture_delivery/readme/DESCRIPTION.rst
odoo/addons/invader_payment_adyen_klarna_capture_delivery/readme/HISTORY.rst
odoo/addons/invader_payment_adyen_klarna_capture_delivery/static/description/index.html
odoo/addons/invader_payment_adyen_klarna_capture_delivery/wizards/adyen_klarna_capture_manual.xml
odoo14_addon_invader_payment_adyen_klarna_capture_delivery-14.0.1.0.1.dist-info/METADATA
odoo14_addon_invader_payment_adyen_klarna_capture_delivery-14.0.1.0.1.dist-info/WHEEL
odoo14_addon_invader_payment_adyen_klarna_capture_delivery-14.0.1.0.1.dist-info/top_level.txt
odoo14_addon_invader_payment_adyen_klarna_capture_delivery-14.0.1.0.1.dist-info/RECORD
